argparsejson/__init__.py
argparsejson/argparsejson.py
argparsejson/schema.json
argparsejson-0.0.6.dist-info/METADATA
argparsejson-0.0.6.dist-info/WHEEL
argparsejson-0.0.6.dist-info/top_level.txt
argparsejson-0.0.6.dist-info/RECORD
