Metadata-Version: 2.1
Name: argparsejson
Version: 0.0.6
Summary: A library that allows converts JSON into an argparse ArgumentParser
Home-page: https://github.com/jon77p/argparsejson
Author: Jon Prentice
Author-email: jon77p@gmail.com
Requires-Dist: jsonschema
